[
    {
        "id": "2",
        "club": "Beira-Mar",
        "stadium": null,
        "logo": "https://cdn-img.zerozero.pt/img/logos/equipas/2_imgbank_1683209128.png",
        "equipamentos": [
            {
                "type": "desconhecido",
                "url": "https://www.zerozero.pt/img/logos/equipas/02/2_shirt_20240221084801_beira_mar.png",
                "alt_text": "beira-mar"
            }
        ],
        "address": null,
        "latitude": 40.6434864,
        "longitude": -8.6542323,
        "url": "https://www.zerozero.pt/equipa/beira-mar/2"
    },
    {
        "id": "2178",
        "club": "Torreense",
        "stadium": "Estádio Manuel Marques",
        "logo": "https://cdn-img.zerozero.pt/img/logos/equipas/2178_imgbank_1682588244.png",
        "equipamentos": [
            {
                "type": "Casa",
                "url": "https://www.zerozero.pt/img/logos/equipas/78/2178_shirt_20241118144730_torreense.png",
                "alt_text": "torreense"
            }
        ],
        "address": null,
        "latitude": 39.09468870445161,
        "longitude": -9.256681547301007,
        "url": "https://www.zerozero.pt/equipa/torreense/2178"
    },
    {
        "id": "3598",
        "club": "Lourinhanense",
        "stadium": "Estádio Municipal da Lourinhã",
        "logo": "https://cdn-img.zerozero.pt/img/logos/equipas/3598_imgbank_1683111100.png",
        "equipamentos": [
            {
                "type": "Casa",
                "url": "https://www.zerozero.pt/img/logos/equipas/98/3598_shirt_20250715150012_lourinhanense.png",
                "alt_text": "lourinhanense"
            }
        ],
        "address": null,
        "latitude": 39.239725857087585,
        "longitude": -9.309107208662232,
        "url": "https://www.zerozero.pt/equipa/lourinhanense/3598"
    },
    {
        "id": "19",
        "club": "Académica OAF",
        "stadium": "Estádio Municipal da Cidade de Coimbra",
        "logo": "https://cdn-img.zerozero.pt/img/logos/equipas/19_imgbank_1752061481.png",
        "equipamentos": [
            {
                "type": "desconhecido",
                "url": "https://www.zerozero.pt/img/logos/equipas/19/19_shirt_20231227103544_academica_oaf.png",
                "alt_text": "académica oaf"
            }
        ],
        "address": null,
        "latitude": 40.20289574659429,
        "longitude": -8.407569212880802,
        "url": "https://www.zerozero.pt/equipa/academica-oaf/19"
    },
    {
        "id": "3",
        "club": "Belenenses",
        "stadium": "Estádio do Restelo",
        "logo": "https://cdn-img.zerozero.pt/img/logos/equipas/3_imgbank_1682589777.png",
        "equipamentos": [
            {
                "type": "desconhecido",
                "url": "https://www.zerozero.pt/img/logos/equipas/03/3_shirt_20250523113255_belenenses.png",
                "alt_text": "belenenses"
            }
        ],
        "address": null,
        "latitude": 38.702135423428984,
        "longitude": -9.207755425230948,
        "url": "https://www.zerozero.pt/equipa/belenenses/3"
    },
    {
        "id": "22",
        "club": "União Madeira",
        "stadium": "",
        "logo": "https://cdn-img.zerozero.pt/img/logos/equipas/22_imgbank.png",
        "equipamentos": [
            {
                "type": "desconhecido",
                "url": "https://www.zerozero.pt/img/logos/equipas/22/22_shirt_20190422104859_u_madeira.png",
                "alt_text": "união madeira"
            }
        ],
        "address": null,
        "latitude": 32.67894354172962,
        "longitude": -16.85744078106183,
        "url": "https://www.zerozero.pt/equipa/uniao-madeira/22"
    },
    {
        "id": "13",
        "club": "Paços de Ferreira",
        "stadium": "Estádio Capital do Móvel",
        "logo": "https://cdn-img.zerozero.pt/img/logos/equipas/13_imgbank_1682583483.png",
        "equipamentos": [
            {
                "type": "desconhecido",
                "url": "https://www.zerozero.pt/img/logos/equipas/13/13_shirt_20241118144651_pacos_de_ferreira.png",
                "alt_text": "paços de ferreira"
            }
        ],
        "address": null,
        "latitude": 41.27144778991801,
        "longitude": -8.385628783445842,
        "url": "https://www.zerozero.pt/equipa/pacos-de-ferreira/13"
    },
    {
        "id": "slbenfica",
        "club": "Benfica",
        "stadium": "Estádio da Luz",
        "logo": "https://cdn-img.zerozero.pt/img/logos/equipas/4_imgbank_1683238034.png",
        "equipamentos": [
            {
                "type": "Casa",
                "url": "https://www.zerozero.pt/img/logos/equipas/04/4_shirt_20241014152915_benfica.png",
                "alt_text": "benfica"
            }
        ],
        "address": null,
        "latitude": 38.7531359493634,
        "longitude": -9.184956307391019,
        "url": "https://www.zerozero.pt/equipa/benfica"
    },
    {
        "id": "23",
        "club": "SC Covilhã",
        "stadium": "Estádio Municipal José dos Santos Pinto",
        "logo": "https://cdn-img.zerozero.pt/img/logos/equipas/23_imgbank_1753175883.png",
        "equipamentos": [
            {
                "type": "desconhecido",
                "url": "https://www.zerozero.pt/img/logos/equipas/23/23_shirt_20231227102116_sc_covilha.png",
                "alt_text": "sc covilhã"
            }
        ],
        "address": null,
        "latitude": 40.283083501011774,
        "longitude": -7.5124140865056,
        "url": "https://www.zerozero.pt/equipa/sc-covilha/23"
    },
    {
        "id": "17",
        "club": "UD Leiria",
        "stadium": "Estádio Dr. Magalhães Pessoa",
        "logo": "https://www.zerozero.pt/img_icon/logos/equipas/17_imgbank_1721993809.png",
        "equipamentos": [
            {
                "type": "desconhecido",
                "url": "https://www.zerozero.pt/img/logos/equipas/17/17_shirt_20241118144735_ud_leiria.png",
                "alt_text": "ud leiria"
            }
        ],
        "address": null,
        "latitude": 39.74900614105751,
        "longitude": -8.813235139326634,
        "url": "https://www.zerozero.pt/equipa/ud-leiria/17"
    },
    {
        "id": "35",
        "club": "Vitória de Setubal",
        "stadium": "",
        "logo": "https://cdn-img.zerozero.pt/img/logos/equipas/35_imgbank_1683027153.png",
        "equipamentos": [
            {
                "type": "desconhecido",
                "url": "https://www.zerozero.pt/img/logos/equipas/35/35_shirt_20240418082008_vitoria_fc.png",
                "alt_text": "vitória fc"
            }
        ],
        "address": null,
        "latitude": 38.53089809122608,
        "longitude": -8.89102867036612,
        "url": "https://www.zerozero.pt/equipa/vitoria-fc/35"
    },
    {
        "id": "18",
        "club": "Vitória de Guimarães",
        "stadium": "Estádio D. Afonso Henriques",
        "logo": "https://cdn-img.zerozero.pt/img/logos/equipas/18_imgbank_1691672368.png",
        "equipamentos": [
            {
                "type": "Casa",
                "url": "https://www.zerozero.pt/img/logos/equipas/18/18_shirt_20241014153008_vitoria_sc.png",
                "alt_text": "vitória sc"
            }
        ],
        "address": null,
        "latitude": 41.4457685813183,
        "longitude": -8.301101264401753,
        "url": "https://www.zerozero.pt/equipa/vitoria-sc"
    },
    {
        "id": "3969",
        "club": "Ponterrolense",
        "stadium": "",
        "logo": "https://cdn-img.zerozero.pt/img/logos/equipas/3969_imgbank.png",
        "equipamentos": [
            {
                "type": "desconhecido",
                "url": "https://www.zerozero.pt/img/logos/equipas/69/3969_shirt_20240911143505_ponterrolense.png",
                "alt_text": "ponterrolense"
            }
        ],
        "address": null,
        "latitude": 39.09684056595246,
        "longitude": -9.326641777038024,
        "url": "https://www.zerozero.pt/equipa/ponterrolense/3969"
    },
    {
        "id": "73330",
        "club": "Varejense Futsal",
        "stadium": "",
        "logo": "https://cdn-img.zerozero.pt/img/logos/equipas/51/287051_logo_varejense.png",
        "equipamentos": [
            {
                "type": "desconhecido",
                "url": "https://www.zerozero.pt/img/logos/equipas/30/73330_shirt_20250701172019_varejense.jpg",
                "alt_text": "varejense "
            }
        ],
        "address": null,
        "latitude": 38.72699529198073,
        "longitude": -9.118399977997736,
        "url": "https://www.zerozero.pt/equipa/varejense-/73330"
    },
    {
        "id": "3543",
        "club": "1º Dezembro",
        "stadium": "Complexo Desportivo Conde de Sucena",
        "logo": "https://cdn-img.zerozero.pt/img/logos/equipas/3543_imgbank_1683278279.png",
        "equipamentos": [
            {
                "type": "desconhecido",
                "url": "https://www.zerozero.pt/img/logos/equipas/43/3543_shirt_20231227103353_1_dezembro.png",
                "alt_text": "1º dezembro"
            }
        ],
        "address": null,
        "latitude": 38.788191243376325,
        "longitude": -9.374552542903107,
        "url": "https://www.zerozero.pt/equipa/1-dezembro/3543"
    },
    {
        "id": "11170",
        "club": "A dos Cunhados",
        "stadium": "Maximino Franco dos Santos",
        "logo": "https://cdn-img.zerozero.pt/img/logos/equipas/11170_imgbank.png",
        "equipamentos": [],
        "address": null,
        "latitude": 39.154314230595524,
        "longitude": -9.289082445210541,
        "url": "https://www.zerozero.pt/equipa/a-dos-cunhados/11170"
    },
    {
        "id": "3936",
        "club": "AD Oeiras",
        "stadium": "",
        "logo": "https://cdn-img.zerozero.pt/img/logos/equipas/3936_imgbank.png",
        "equipamentos": [
            {
                "type": "desconhecido",
                "url": "https://www.zerozero.pt/img/logos/equipas/36/3936_shirt_20250723100324_oeiras.png",
                "alt_text": "ad oeiras"
            }
        ],
        "address": null,
        "latitude": 38.68598819894692,
        "longitude": -9.313964931991666,
        "url": "https://www.zerozero.pt/equipa/ad-oeiras/3936"
    }
]